poetry_release_test/README.md
poetry_release_test/__init__.py
poetry_release_test/test/__init__.py
poetry_release_test/tests/__init__.py
poetry_release_test-0.0.0.dist-info/WHEEL
poetry_release_test-0.0.0.dist-info/METADATA
poetry_release_test-0.0.0.dist-info/RECORD
