Metadata-Version: 2.1
Name: poetry-release-test
Version: 0.0.0
Summary: test release through poetry
Author: songhaoyanga
Author-email: 1627635056@qq.com
Requires-Python: >=3.8,<4.0
Classifier: Programming Language :: Python :: 3
Classifier: Programming Language :: Python :: 3.8
Classifier: Programming Language :: Python :: 3.9
Classifier: Programming Language :: Python :: 3.10
Classifier: Programming Language :: Python :: 3.11
